{
    "members": [
        {
        "name": "The Major Company",
        "address": "1234 Wrigley Way",
        "phoneNumber": 4088881234,
        "website": "themajorcompany.com",
        "imageIcon": "https://www.pexels.com/photo/blue-and-gray-high-rise-building-162031/",
        "memberlevel": 1
    },
    {
        "name": "The Major Company",
        "address": "1234 Wrigley Way",
        "phonenumber": 4088881234,
        "websiteURL": "themajorcompany.com",
        "imageicon": "https://www.pexels.com/photo/blue-and-gray-high-rise-building-162031/",
        "memberlevel": 1
    },
    {
        "name": "The Major Company",
        "address": "1234 Wrigley Way",
        "phonenumber": 4088881234,
        "websiteURL": "themajorcompany.com",
        "imageicon": "https://www.pexels.com/photo/blue-and-gray-high-rise-building-162031/",
        "memberlevel": 1
    },
    {
        "name": "The Major Company",
        "address": "1234 Wrigley Way",
        "phonenumber": 4088881234,
        "websiteURL": "themajorcompany.com",
        "imageicon": "https://www.pexels.com/photo/blue-and-gray-high-rise-building-162031/",
        "memberlevel": 1
    },
    {
        "name": "The Major Company",
        "address": "1234 Wrigley Way",
        "phonenumber": 4088881234,
        "websiteURL": "themajorcompany.com",
        "imageicon": "https://www.pexels.com/photo/blue-and-gray-high-rise-building-162031/",
        "memberlevel": 1
    },
    {
        "name": "The Major Company",
        "address": "1234 Wrigley Way",
        "phonenumber": 4088881234,
        "websiteURL": "themajorcompany.com",
        "imageicon": "https://www.pexels.com/photo/blue-and-gray-high-rise-building-162031/",
        "memberlevel": 1
    },
    {
        "name": "The Major Company",
        "address": "1234 Wrigley Way",
        "phonenumber": 4088881234,
        "websiteURL": "themajorcompany.com",
        "imageicon": "https://www.pexels.com/photo/blue-and-gray-high-rise-building-162031/",
        "memberlevel": 1
    }
    ]
}